breds/bootstrapping.py
breds/breds_tuple.py
breds/cli.py
breds/commons.py
breds/config.py
breds/parameters.cfg
breds/pattern.py
breds/reverb.py
breds/seed.py
breds/sentence.py
breds-1.0.1.dist-info/LICENSE.txt
breds-1.0.1.dist-info/METADATA
breds-1.0.1.dist-info/WHEEL
breds-1.0.1.dist-info/entry_points.txt
breds-1.0.1.dist-info/top_level.txt
breds-1.0.1.dist-info/RECORD
