Metadata-Version: 2.1
Name: breds
Version: 1.0.1
Summary: Bootstrapping Relationship Extraction with Distributional Semantics
Author-email: "David S. Batista" <dsbatista@gmail.com>
License: GNU GPLv3
Project-URL: homepage, https://github.com/davidsbatista/BREDS
Project-URL: documentation, https://www.davidsbatista.net/assets/documents/publications/breds-emnlp_15.pdf
Project-URL: repository, https://github.com/davidsbatista/BREDS
Keywords: nlp,semantic relationship extraction,bootstrapping,emnlp,vector representations,word embeddings,word2vec,phrase embeddings
Classifier: Topic :: Text Processing :: Linguistic
Classifier: Programming Language :: Python :: 3
Requires-Python: >=3.9
License-File: LICENSE.txt
Requires-Dist: gensim (>=3.7.3)
Requires-Dist: nltk (>=3.4.1)
Requires-Dist: numpy (>=1.16.3)
